tylerproblemprint/PPrint.py
tylerproblemprint/__init__.py
tylerproblemprint-0.1.0.dist-info/METADATA
tylerproblemprint-0.1.0.dist-info/WHEEL
tylerproblemprint-0.1.0.dist-info/licenses/LICENSE
tylerproblemprint-0.1.0.dist-info/RECORD
