Metadata-Version: 2.4
Name: tylerproblemprint
Version: 0.1.0
Summary: Print homework solutions in an organized unicode box format with automatic problem tracking.
Project-URL: Homepage, https://github.com/<your-username>/<your-repo>
Author: Tyler Black
License: MIT License
License-File: LICENSE
Keywords: formatting,homework,printing,utility
Requires-Python: >=3.10
